individous_wrapper/__init__.py
individous_wrapper/video.py
individous_wrapper-0.0.1.dist-info/METADATA
individous_wrapper-0.0.1.dist-info/WHEEL
individous_wrapper-0.0.1.dist-info/top_level.txt
individous_wrapper-0.0.1.dist-info/RECORD
