Metadata-Version: 2.1
Name: individous-wrapper
Version: 0.0.1
Summary: Get data from youtube with individous
Home-page: UNKNOWN
Author: Jonathan Krüger
Author-email: <jonathan@mag-roboter.de>
License: UNKNOWN
Keywords: python,youtube,individous,wrapper
Platform: UNKNOWN
Classifier: Development Status :: 1 - Planning
Classifier: Intended Audience :: Developers
Classifier: Programming Language :: Python :: 3
Classifier: Operating System :: Unix
Requires-Dist: bs4
Requires-Dist: requests
